LICENSE
MANIFEST.in
README.md
setup.py
bom_open/__init__.py
bom_open/bom_open.py
bom_open.egg-info/PKG-INFO
bom_open.egg-info/SOURCES.txt
bom_open.egg-info/dependency_links.txt
bom_open.egg-info/requires.txt
bom_open.egg-info/top_level.txt