Metadata-Version: 2.1
Name: bom-open
Version: 0.3.2
Summary: Python file/stdio context manager which detects encoding
Home-page: https://github.com/timrburnham/bom_open
Author: Tim Burnham
Author-email: timrburnham@gmail.com
License: unlicense.org
Platform: UNKNOWN
